flask_trace_util/__init__.py
flask_trace_util/flask_trace.py
flask_trace_util/gunicorn_logger.py
flask_trace_util/util.py
flask_trace_util-0.4.10.dist-info/LICENSE
flask_trace_util-0.4.10.dist-info/METADATA
flask_trace_util-0.4.10.dist-info/WHEEL
flask_trace_util-0.4.10.dist-info/top_level.txt
flask_trace_util-0.4.10.dist-info/RECORD
