Metadata-Version: 2.1
Name: flask-trace-util
Version: 0.4.10
Summary: Trace utility for flask
Home-page: https://github.com/akin-tekeoglu/flask-trace-util
Author: Akın Tekeoğlu
Author-email: akin.tekeoglu@gmail.com
License: UNKNOWN
Platform: UNKNOWN
Classifier: Programming Language :: Python :: 3.7
Classifier: License :: OSI Approved :: MIT License
Classifier: Operating System :: OS Independent
Requires-Python: >=3.7
Requires-Dist: Flask
Requires-Dist: requests
Requires-Dist: opencensus
Requires-Dist: opencensus-ext-stackdriver
Requires-Dist: python-json-logger
